MANIFEST.in
README.txt
setup.cfg
setup.py
csci/__init__.py
csci.shortlinks.egg-info/PKG-INFO
csci.shortlinks.egg-info/SOURCES.txt
csci.shortlinks.egg-info/dependency_links.txt
csci.shortlinks.egg-info/entry_points.txt
csci.shortlinks.egg-info/namespace_packages.txt
csci.shortlinks.egg-info/not-zip-safe
csci.shortlinks.egg-info/paster_plugins.txt
csci.shortlinks.egg-info/requires.txt
csci.shortlinks.egg-info/top_level.txt
csci/shortlinks/README.txt
csci/shortlinks/__init__.py
csci/shortlinks/config.py
csci/shortlinks/configure.zcml
csci/shortlinks/form.py
csci/shortlinks/browser/__init__.py
csci/shortlinks/browser/configure.zcml
csci/shortlinks/browser/google_short.py
csci/shortlinks/browser/newlink.py
csci/shortlinks/browser/newlinkview.cpt
csci/shortlinks/browser/newlinkview.pt
csci/shortlinks/browser/newlinkview.py
csci/shortlinks/content/__init__.py
csci/shortlinks/content/configure.zcml
csci/shortlinks/content/shortlinks.py
csci/shortlinks/interfaces/__init__.py
csci/shortlinks/interfaces/shortlinks.py
csci/shortlinks/portlets/__init__.py
csci/shortlinks/portlets/configure.zcml
csci/shortlinks/profiles/default/factorytool.xml
csci/shortlinks/profiles/default/metadata.xml
csci/shortlinks/profiles/default/portlets.xml
csci/shortlinks/profiles/default/rolemap.xml
csci/shortlinks/profiles/default/types.xml
csci/shortlinks/profiles/default/types/shortlinks.xml
csci/shortlinks/tests/__init__.py
csci/shortlinks/tests/base.py
csci/shortlinks/tests/test_doctest.py