Metadata-Version: 1.0
Name: csci.shortlinks
Version: 0.1dev
Summary: UNKNOWN
Home-page: www.cannonscientific.com
Author: Peter Dyson
Author-email: pdyson@cannonscientific.com
License: GPL
Keywords: plone google shortlink short link
Platform: UNKNOWN
Classifier: Framework :: Plone
Classifier: Intended Audience :: Developers
Classifier: Topic :: Software Development :: Libraries :: Python Modules
Classifier: License :: OSI Approved :: GNU General Public License (GPL)
